jinjaq/__init__.py
jinjaq/core.py
jinjaq-0.1.0.dist-info/LICENSE
jinjaq-0.1.0.dist-info/METADATA
jinjaq-0.1.0.dist-info/WHEEL
jinjaq-0.1.0.dist-info/RECORD
