Metadata-Version: 2.1
Name: jinjaq
Version: 0.1.0
Summary: Jinja Query Templates for SQL
Home-page: https://github.com/antonrh/jinjaq
License: MIT
Keywords: sql,query,queries,template,jinja,database,db
Author: Anton Ruhlov
Author-email: antonruhlov@gmail.com
Requires-Python: >=3.8,<4.0
Classifier: License :: OSI Approved :: MIT License
Classifier: Programming Language :: Python :: 3
Classifier: Programming Language :: Python :: 3.8
Classifier: Programming Language :: Python :: 3.9
Classifier: Programming Language :: Python :: 3.10
Classifier: Programming Language :: Python :: 3.11
Provides-Extra: docs
Requires-Dist: jinja2 (>=3.1.2,<4.0.0)
Requires-Dist: mkdocs (>=1.4.2,<2.0.0) ; extra == "docs"
Requires-Dist: mkdocs-material (>=9.1.13,<10.0.0) ; extra == "docs"
Project-URL: Repository, https://github.com/antonrh/jinjaq
